Metadata-Version: 2.1
Name: pynamodb-polymorph
Version: 0.3.3
Summary: Calculated/copied attributes to support advanced single-table design in DynamoDB
Home-page: https://github.com/ryansb/pynamodb-polymorph
License: MIT
Platform: UNKNOWN
Classifier: Intended Audience :: Developers
Classifier: Operating System :: OS Independent
Classifier: Programming Language :: Python :: 3.9
Classifier: Programming Language :: Python :: 3.8
Requires-Python: >=3.8
Provides-Extra: testing
